broccoli/__init__.py
broccoli/activation.py
broccoli/cnn.py
broccoli/linear.py
broccoli/rope.py
broccoli/tensor.py
broccoli/transformer.py
broccoli/utils.py
broccoli/vit.py
broccoli_ml-15.2.0.dist-info/LICENSE
broccoli_ml-15.2.0.dist-info/METADATA
broccoli_ml-15.2.0.dist-info/WHEEL
broccoli_ml-15.2.0.dist-info/RECORD
