Metadata-Version: 2.3
Name: broccoli-ml
Version: 15.2.0
Summary: Some useful Pytorch models, circa 2025
License: MIT
Author: Nicholas Bailey
Requires-Python: >=3.8
Classifier: License :: OSI Approved :: MIT License
Classifier: Programming Language :: Python :: 3
Classifier: Programming Language :: Python :: 3.8
Classifier: Programming Language :: Python :: 3.9
Classifier: Programming Language :: Python :: 3.10
Classifier: Programming Language :: Python :: 3.11
Classifier: Programming Language :: Python :: 3.12
Classifier: Programming Language :: Python :: 3.13
Requires-Dist: einops (>=0.8.1,<0.9.0)
